{
	"DISCORD_PERMISSION_MANAGE_MESSAGES": "Administrează Mesaje",
	"MESSAGEABLE_EMPTY_MESSAGE": "Am încercat să trimit un mesaj gol.",
	"MESSAGEABLE_SEND_FAIL": "Hopa! Rezultatul a devenit mai mare de 2000 de caractere. Aici este un fișier text în care se află conținutul:",
	"MESSAGEABLE_UPDATE_FAIL": "Hopa! Rezultatul a devenit mai mare de 2000 de caractere.",
	"PAGINATION_ALTERNATIVE_CLOSE": "Scrie `x` pentru a închide paginarea.",
	"PAGINATION_ALTERNATIVE_NAVIGATION": "Scrie `<` sau `>` pentru a schimba pagina. Scrie `p<Număr>` pentru a sări la o pagină (ex. `p10`).",
	"PAGINATION_NO_ITEMS": "Nimic înafară de noi doi aici...",
	"PAGINATION_NO_MANAGE_MESSAGES": "Se pare că nu am permisiunea `{permission}`. O să șterg automat paginile schimbând mesaje dacă această permisiune este dată.",
	"PAGINATION_PAGE": "Pagina {numPage, number}/{numMax, number}"
}
